setup.py
douglas/__init__.py
douglas/douglas.py
douglas/setup.py
planex/__init__.py
planex/planex.py
planex.egg-info/PKG-INFO
planex.egg-info/SOURCES.txt
planex.egg-info/dependency_links.txt
planex.egg-info/requires.txt
planex.egg-info/top_level.txt
telma/__init__.py
telma/setup.py
telma/telma.py