Metadata-Version: 2.1
Name: planex
Version: 0.0.2
Summary: Modulo que guarda la base de la prestaciones de los participes de un plan de pensiones de prestacion definida. USELESS
Home-page: UNKNOWN
Author: José Valencia Figueroa
Author-email: joel.jvalencia@gmail.com
License: UNKNOWN
Keywords: insurance,actuarial science,life insurance,pension,python,spain,life contingencies
Platform: UNKNOWN
Classifier: Programming Language :: Python :: 3
Classifier: License :: OSI Approved :: MIT License
Classifier: Operating System :: OS Independent
